README.md
setup.cfg
setup.py
conf/backup1.xml
conf/backup2.xml
conf/backup3.xml
conf/mjbackupConfig.xml
conf/mjbackupMysql.conf
conf/mjbackupPgsql.conf
conf/mjsync.conf
mjbackup/__init__.py
mjbackup/mjbackup.py
mjbackup/mjbackupConfig.py
mjbackup/mjbackupFiles.py
mjbackup/mjbackupMysql.py
mjbackup/mjbackupPgsql.py
mjbackup/mjsync.py
mjbackup.egg-info/PKG-INFO
mjbackup.egg-info/SOURCES.txt
mjbackup.egg-info/dependency_links.txt
mjbackup.egg-info/top_level.txt