Metadata-Version: 2.1
Name: mjbackup
Version: 1.0.1
Summary: Morning Joe Software Linux Server Backup System
Home-page: https://www.morningjoesoftware.com
Author: morningjoe
Author-email: morningjoe@morningjoesoftware.com
License: UNKNOWN
Download-URL: https://github.com/morningjoesoftware/mjbackup/archive/v1.0.1.tar.gz
Platform: posix
Classifier: Programming Language :: Python :: 3
Classifier: Development Status :: 4 - Beta
Classifier: Environment :: Console
Classifier: Intended Audience :: Developers
Classifier: Intended Audience :: System Administrators
Classifier: Intended Audience :: Information Technology
Classifier: License :: OSI Approved :: MIT License
Classifier: Operating System :: POSIX :: Linux
Classifier: Operating System :: POSIX
Classifier: Topic :: System :: Archiving :: Backup
Classifier: Topic :: System :: Archiving :: Compression
Requires-Python: >=3.6
